{"SN2016gjw": {"schema": "https://github.com/astrocatalogs/supernovae/blob/d3ef5fc/SCHEMA.md", "name": "SN2016gjw", "sources": [{"name": "2016A&A...594A..13P", "bibcode": "2016A&A...594A..13P", "reference": "Planck Collaboration et al. (2016)", "alias": "1"}, {"name": "2012PASP..124..668Y", "bibcode": "2012PASP..124..668Y", "reference": "Yaron & Gal-Yam (2012)", "alias": "2"}, {"name": "2011ApJ...737..103S", "bibcode": "2011ApJ...737..103S", "reference": "Schlafly & Finkbeiner (2011)", "alias": "3"}, {"name": "Gaia Photometric Science Alerts", "url": "https://gsaweb.ast.cam.ac.uk/alerts/alert/Gaia16biv", "alias": "4"}, {"name": "CPCS Alert 26385", "url": "http://gsaweb.ast.cam.ac.uk/followup/get_alert_lc_data?alert_id=26385", "alias": "5"}, {"name": "Transient Name Server", "url": "https://wis-tns.weizmann.ac.il/", "alias": "6"}, {"name": "Cambridge Photometric Calibration Server", "secondary": true, "url": "http://gsaweb.ast.cam.ac.uk/followup/", "alias": "7"}, {"name": "Latest Supernovae", "secondary": true, "url": "http://www.rochesterastronomy.org/snimages/snredshiftall.html", "alias": "8"}, {"name": "The Open Supernova Catalog", "bibcode": "2017ApJ...835...64G", "reference": "Guillochon et al. (2017)", "secondary": true, "url": "https://sne.space", "alias": "9"}], "alias": [{"value": "SN2016gjw", "source": "2,4,6,8"}, {"value": "AT2016gjw", "source": "2,4,8"}, {"value": "Gaia16biv", "source": "4,7,8"}, {"value": "iPTF16gjw", "source": "2"}], "claimedtype": [{"value": "Ia", "source": "4,8"}], "comovingdist": [{"value": "284.64", "derived": true, "u_value": "Mpc", "source": "1,4,8,9"}], "dec": [{"value": "+29:58:55.63", "u_value": "degrees", "source": "4,8"}, {"value": "+29:58:55.56", "u_value": "degrees", "source": "4,7"}], "discoverdate": [{"value": "2016/09/19", "source": "4,8"}], "discoverer": [{"value": "Gaia", "source": "4,8"}], "ebv": [{"value": "0.038", "derived": true, "e_value": "0.0005", "source": "3,9"}], "lumdist": [{"value": "303.227", "derived": true, "u_value": "Mpc", "source": "1,4,8,9"}], "maxabsmag": [{"value": "-19.3301", "derived": true, "source": "1,4,8,9"}], "maxappmag": [{"value": "18.01", "derived": true, "source": "5,7,9"}], "maxband": [{"value": "g", "derived": true, "source": "5,7,9"}], "maxdate": [{"value": "2016/09/23", "derived": true, "source": "5,7,9"}], "maxvisualabsmag": [{"value": "-19.3988", "derived": true, "source": "1,4,8,9"}], "maxvisualappmag": [{"value": "18.01", "derived": true, "source": "5,7,9"}], "maxvisualband": [{"value": "g", "derived": true, "source": "5,7,9"}], "maxvisualdate": [{"value": "2016/09/23", "derived": true, "source": "5,7,9"}], "ra": [{"value": "08:29:33.083", "u_value": "hours", "source": "4,8"}, {"value": "08:29:33.12", "u_value": "hours", "source": "4,7"}], "redshift": [{"value": "0.065316", "source": "4,8"}], "velocity": [{"value": "18943", "u_value": "km/s", "source": "9"}], "photometry": [{"time": "54832.5", "band": "R", "instrument": "CFH12k", "magnitude": "21.5", "observer": "iPTF", "telescope": "P48", "u_time": "MJD", "upperlimit": true, "source": "6"}, {"time": "57513.3609954", "band": "G", "instrument": "Astrometric", "magnitude": "21.5", "observer": "Robot", "telescope": "Gaia", "u_time": "MJD", "upperlimit": true, "source": "6"}, {"time": "57650.1369907", "band": "G", "e_magnitude": "0.2", "instrument": "Astrometric", "magnitude": "18.74", "observer": "Robot", "telescope": "Gaia", "u_time": "MJD", "source": "6"}, {"time": "57650.138", "band": "G", "e_magnitude": "0.0", "instrument": "Astrometric", "magnitude": "18.76", "telescope": "GAIA", "u_time": "MJD", "source": "4"}, {"time": "57650.314", "band": "G", "e_magnitude": "0.0", "instrument": "Astrometric", "magnitude": "18.76", "telescope": "GAIA", "u_time": "MJD", "source": "4"}, {"time": "57653.2437", "band": "g", "e_magnitude": "0.0203", "magnitude": "18.1205", "observatory": "Mercator Geneva Grou", "u_time": "MJD", "source": "5,7"}, {"time": "57654.2421", "band": "g", "e_magnitude": "0.0185", "magnitude": "18.0083", "observatory": "Mercator Geneva Grou", "u_time": "MJD", "source": "5,7"}, {"time": "57655.2413", "band": "r", "e_magnitude": "0.0136", "magnitude": "18.1966", "observatory": "Mercator Geneva Grou", "u_time": "MJD", "source": "5,7"}, {"time": "57656.2365", "band": "g", "e_magnitude": "0.0197", "magnitude": "18.0753", "observatory": "Mercator Geneva Grou", "u_time": "MJD", "source": "5,7"}, {"time": "57657.2391", "band": "r", "e_magnitude": "0.0141", "magnitude": "18.9716", "observatory": "Mercator Geneva Grou", "u_time": "MJD", "source": "5,7"}, {"time": "57671.567", "band": "G", "e_magnitude": "0.0", "instrument": "Astrometric", "magnitude": "19.74", "telescope": "GAIA", "u_time": "MJD", "source": "4"}, {"time": "57671.641", "band": "G", "e_magnitude": "0.0", "instrument": "Astrometric", "magnitude": "19.74", "telescope": "GAIA", "u_time": "MJD", "source": "4"}, {"time": "57674.535", "band": "R", "instrument": "CFH12k", "magnitude": "19.492", "observer": "iPTF", "telescope": "P48", "u_time": "MJD", "source": "6"}], "spectra": [{"time": "57679.5", "instrument": "SED-Machine", "observer": "Walter", "survey": "iPTF", "telescope": "P60", "u_fluxes": "erg/s/cm^2/Angstrom", "u_time": "MJD", "u_wavelengths": "Angstrom", "data": [["4278.8", "1.5095e-17"], ["4296.7", "-1.4242e-17"], ["4314.7", "1.9634e-17"], ["4332.7", "1.1210e-18"], ["4350.9", "1.1940e-17"], ["4369.1", "-5.3696e-18"], ["4387.3", "-1.4058e-17"], ["4405.7", "3.0072e-17"], ["4424.1", "1.4524e-17"], ["4442.6", "1.4472e-17"], ["4461.2", "4.1418e-17"], ["4479.9", "-6.0046e-18"], ["4498.6", "1.3957e-18"], ["4517.5", "2.4306e-17"], ["4536.4", "-1.0710e-18"], ["4555.3", "1.0327e-17"], ["4574.4", "3.0424e-17"], ["4593.5", "-6.0263e-19"], ["4612.8", "3.4566e-17"], ["4632.1", "2.9977e-17"], ["4651.4", "3.3273e-17"], ["4670.9", "1.7944e-18"], ["4690.5", "5.2715e-18"], ["4710.1", "2.8972e-17"], ["4729.8", "1.3207e-17"], ["4749.6", "2.6501e-17"], ["4769.4", "3.6821e-17"], ["4789.4", "1.8434e-17"], ["4809.4", "2.6958e-17"], ["4829.6", "4.3481e-18"], ["4849.8", "2.3672e-17"], ["4870.1", "3.4011e-17"], ["4890.4", "9.1493e-18"], ["4910.9", "1.1132e-17"], ["4931.4", "2.0762e-17"], ["4952.1", "1.8175e-17"], ["4972.8", "1.9452e-17"], ["4993.6", "1.4854e-17"], ["5014.5", "1.5831e-17"], ["5035.5", "4.9274e-18"], ["5056.6", "2.9130e-17"], ["5077.7", "1.2778e-17"], ["5099.0", "1.2672e-17"], ["5120.3", "7.0560e-18"], ["5141.7", "-3.2493e-18"], ["5163.2", "9.7648e-18"], ["5184.8", "1.4332e-17"], ["5206.5", "2.5066e-17"], ["5228.3", "2.7853e-17"], ["5250.2", "1.9812e-17"], ["5272.2", "4.8565e-18"], ["5294.2", "2.5076e-17"], ["5316.4", "2.1658e-17"], ["5338.6", "1.5611e-17"], ["5360.9", "9.5984e-18"], ["5383.4", "2.9672e-17"], ["5405.9", "1.9599e-17"], ["5428.5", "1.4900e-17"], ["5451.2", "5.7488e-18"], ["5474.0", "5.7938e-18"], ["5496.9", "1.4279e-18"], ["5519.9", "1.0957e-17"], ["5543.0", "2.4373e-17"], ["5566.2", "2.5294e-17"], ["5589.5", "3.3866e-17"], ["5612.9", "3.2239e-17"], ["5636.4", "1.8783e-17"], ["5660.0", "2.1841e-17"], ["5683.7", "2.8759e-17"], ["5707.4", "3.4723e-17"], ["5731.3", "2.8316e-17"], ["5755.3", "2.7851e-17"], ["5779.4", "4.2512e-17"], ["5803.6", "3.9550e-17"], ["5827.8", "4.1359e-17"], ["5852.2", "2.9061e-17"], ["5876.7", "2.6577e-17"], ["5901.3", "3.6818e-17"], ["5926.0", "4.5868e-17"], ["5950.8", "5.4950e-17"], ["5975.7", "4.6375e-17"], ["6000.7", "3.2652e-17"], ["6025.8", "3.2322e-17"], ["6051.0", "3.5902e-17"], ["6076.3", "3.6918e-17"], ["6101.8", "3.5307e-17"], ["6127.3", "3.4850e-17"], ["6152.9", "4.4805e-17"], ["6178.7", "2.8841e-17"], ["6204.5", "2.9635e-17"], ["6230.5", "2.8995e-17"], ["6256.6", "3.0282e-17"], ["6282.7", "4.0850e-17"], ["6309.0", "2.1718e-17"], ["6335.4", "1.9503e-17"], ["6361.9", "2.1352e-17"], ["6388.5", "2.3911e-17"], ["6415.3", "2.2411e-17"], ["6442.1", "1.5536e-17"], ["6469.1", "2.3793e-17"], ["6496.1", "2.8462e-17"], ["6523.3", "2.9910e-17"], ["6550.6", "2.2352e-17"], ["6578.0", "2.4116e-17"], ["6605.5", "3.0734e-17"], ["6633.2", "2.6151e-17"], ["6660.9", "2.3753e-17"], ["6688.8", "2.4136e-17"], ["6716.8", "2.4042e-17"], ["6744.9", "2.5839e-17"], ["6773.1", "2.6528e-17"], ["6801.5", "3.1565e-17"], ["6829.9", "3.8650e-17"], ["6858.5", "4.3709e-17"], ["6887.2", "4.5248e-17"], ["6916.0", "4.8157e-17"], ["6944.9", "4.9441e-17"], ["6974.0", "4.1485e-17"], ["7003.2", "4.0518e-17"], ["7032.5", "4.0038e-17"], ["7061.9", "3.0721e-17"], ["7091.5", "2.0182e-17"], ["7121.1", "2.1743e-17"], ["7150.9", "1.4010e-17"], ["7180.8", "1.6912e-17"], ["7210.9", "1.9559e-17"], ["7241.1", "1.6379e-17"], ["7271.4", "1.4988e-17"], ["7301.8", "2.1503e-17"], ["7332.3", "1.9335e-17"], ["7363.0", "1.9805e-17"], ["7393.8", "1.8958e-17"], ["7424.8", "1.6808e-17"], ["7455.8", "1.7087e-17"], ["7487.0", "1.5953e-17"], ["7518.3", "1.7894e-17"], ["7549.8", "2.4863e-17"], ["7581.4", "2.5130e-17"], ["7613.1", "2.1319e-17"], ["7645.0", "1.9333e-17"], ["7677.0", "2.7336e-17"], ["7709.1", "2.6637e-17"], ["7741.3", "2.1889e-17"], ["7773.7", "1.7639e-17"], ["7806.2", "2.0032e-17"], ["7838.9", "1.9612e-17"], ["7871.7", "2.1822e-17"], ["7904.6", "2.4906e-17"], ["7937.7", "2.8783e-17"], ["7970.9", "2.0773e-17"], ["8004.3", "1.9729e-17"], ["8037.8", "2.2970e-17"], ["8071.4", "2.3131e-17"], ["8105.2", "2.0827e-17"], ["8139.1", "2.0891e-17"], ["8173.1", "2.7910e-17"], ["8207.3", "2.9624e-17"], ["8241.7", "3.2735e-17"], ["8276.2", "3.2103e-17"], ["8310.8", "2.6004e-17"], ["8345.6", "2.6665e-17"], ["8380.5", "2.5979e-17"], ["8415.5", "3.0797e-17"], ["8450.8", "3.9112e-17"], ["8486.1", "3.8026e-17"], ["8521.6", "3.7780e-17"], ["8557.3", "3.1392e-17"], ["8593.1", "2.3841e-17"], ["8629.0", "2.1012e-17"], ["8665.1", "1.6523e-17"], ["8701.4", "1.4523e-17"], ["8737.8", "1.6865e-17"], ["8774.4", "1.1101e-17"], ["8811.1", "2.7559e-18"], ["8847.9", "-8.1764e-19"], ["8885.0", "4.1598e-18"], ["8922.1", "3.4873e-18"], ["8959.5", "5.5141e-18"], ["8997.0", "1.3661e-17"], ["9034.6", "1.4905e-17"], ["9072.4", "1.5845e-17"], ["9110.4", "1.4394e-17"], ["9148.5", "1.6085e-17"], ["9186.8", "1.0274e-17"], ["9225.2", "1.2738e-17"], ["9263.8", "1.4281e-17"], ["9302.6", "1.5225e-17"], ["9341.5", "1.6521e-17"], ["9380.6", "1.5648e-17"], ["9419.8", "1.4281e-17"], ["9459.2", "1.0455e-17"], ["9498.8", "8.2590e-18"], ["9538.6", "7.2677e-18"], ["9578.5", "3.4724e-18"], ["9618.5", "7.0328e-18"], ["9658.8", "9.9889e-18"], ["9699.2", "6.6343e-18"], ["9739.8", "5.2175e-18"], ["9780.5", "8.0749e-18"], ["9821.5", "1.0440e-17"], ["9862.5", "6.0319e-18"], ["9903.8", "5.4988e-18"], ["9945.3", "7.2165e-18"], ["9986.9", "5.1498e-18"], ["10028.7", "6.3969e-18"], ["10070.6", "5.4262e-18"], ["10112.7", "2.6013e-18"], ["10155.1", "-5.5599e-19"], ["10197.6", "-3.3547e-19"], ["10240.2", "2.2727e-18"], ["10283.1", "2.5337e-18"], ["10326.1", "1.5944e-18"], ["10369.3", "3.9531e-18"], ["10412.7", "5.6963e-18"], ["10456.2", "2.8519e-18"]], "source": "6"}], "host7DCD": [{"value": 24.45845389192033, "source": "2534"}], "hostNED_mag": [{"value": 16.6, "source": "2534"}], "hostNED_name": [{"value": "2MASX J08293296+2958513", "source": "2534"}], "hostNED_redshift": [{"value": 0.065316, "source": "2534"}], "hostNED_type": [{"value": "G", "source": "2534"}], "hostNED_vel": [{"value": 19581.0, "source": "2534"}], "hostb": [{"value": 33.22237574058861, "source": "2534"}], "hostbatchID": [{"value": 1038846, "source": "2534"}], "hostbestDetection": [{"value": 1, "source": "2534"}], "hostbeta": [{"value": 10.644449696115835, "source": "2534"}], "hostcx": [{"value": -0.5259533205554339, "source": "2534"}], "hostcy": [{"value": 0.6882307359957718, "source": "2534"}], "hostcz": [{"value": 0.4997114753809755, "source": "2534"}], "hostdecMean": [{"value": 29.9809132, "source": "2534"}], "hostdecMeanErr": [{"value": 0.004379999823868275, "source": "2534"}], "hostdecStack": [{"value": 29.98092862, "source": "2534"}], "hostdecStackErr": [{"value": 0.0010000000474974509, "source": "2534"}], "hostdist": [{"value": 4.503118182684536, "source": "2534"}], "hostdist/DLR": [{"value": 0.380414614832448, "source": "2534"}], "hostdvoRegionID": [{"value": 40975, "source": "2534"}], "hostepochMean": [{"value": 55974.83359954, "source": "2534"}], "hostg-r": [{"value": 0.41720008850097656, "source": "2534"}], "hostg-rErr": [{"value": 0.0017390555511130961, "source": "2534"}], "hostgApFillFac": [{"value": 0.9059590101242064, "source": "2534"}], "hostgApFlux": [{"value": 0.0003425450122449547, "source": "2534"}], "hostgApFluxErr": [{"value": 4.6824999344607926e-07, "source": "2534"}], "hostgApMag": [{"value": 17.563199996948242, "source": "2534"}], "hostgApMagErr": [{"value": 0.0013670000480487945, "source": "2534"}], "hostgApMag_gKronMag": [{"value": 0.95779991149902, "source": "2534"}], "hostgApRadius": [{"value": 3.25, "source": "2534"}], "hostgEpoch": [{"value": 55951.3455566, "source": "2534"}], "hostgExtNSigma": [{"value": 41.4099006652832, "source": "2534"}], "hostgKronFlux": [{"value": 0.0008276469889096916, "source": "2534"}], "hostgKronFluxErr": [{"value": 2.195849901909241e-06, "source": "2534"}], "hostgKronMag": [{"value": 16.605400085449222, "source": "2534"}], "hostgKronMagErr": [{"value": 0.002652999944984913, "source": "2534"}], "hostgKronRad": [{"value": 11.180299758911133, "source": "2534"}], "hostgPSFFlux": [{"value": 0.00012110899842809886, "source": "2534"}], "hostgPSFFluxErr": [{"value": 4.933249897476344e-07, "source": "2534"}], "hostgPSFMag": [{"value": 18.692100524902344, "source": "2534"}], "hostgPSFMagErr": [{"value": 0.00407300004735589, "source": "2534"}], "hostgPlateScale": [{"value": 0.25, "source": "2534"}], "hostgdec": [{"value": 29.98095107, "source": "2534"}], "hostgdecErr": [{"value": 0.0023040201049298052, "source": "2534"}], "hostgexpTime": [{"value": 602.0, "source": "2534"}], "hostginfoFlag": [{"value": 262160391.0, "source": "2534"}], "hostginfoFlag2": [{"value": 524416.0, "source": "2534"}], "hostginfoFlag3": [{"value": 196608.0, "source": "2534"}], "hostgippDetectID": [{"value": 3704.0, "source": "2534"}], "hostgmomentR1": [{"value": 4.4721198081970215, "source": "2534"}], "hostgmomentRH": [{"value": 1.258970022201538, "source": "2534"}], "hostgmomentXX": [{"value": 0.4300560057163239, "source": "2534"}], "hostgmomentXY": [{"value": 0.006729859858751297, "source": "2534"}], "hostgmomentYY": [{"value": 0.4231790006160736, "source": "2534"}], "hostgnFrames": [{"value": 12.0, "source": "2534"}], "hostgpsfChiSq": [{"value": 76.7562026977539, "source": "2534"}], "hostgpsfCore": [{"value": 0.2653209865093231, "source": "2534"}], "hostgpsfLikelihood": [{"value": 0.0, "source": "2534"}], "hostgpsfMajorFWHM": [{"value": 1.306249976158142, "source": "2534"}], "hostgpsfMinorFWHM": [{"value": 1.2680000066757202, "source": "2534"}], "hostgpsfQf": [{"value": 0.99924898147583, "source": "2534"}], "hostgpsfQfPerfect": [{"value": 0.99924898147583, "source": "2534"}], "hostgpsfTheta": [{"value": -7.332159996032715, "source": "2534"}], "hostgra": [{"value": 127.38743998, "source": "2534"}], "hostgraErr": [{"value": 0.002381419995799661, "source": "2534"}], "hostgsky": [{"value": 1.4620099575424206e-09, "source": "2534"}], "hostgskyErr": [{"value": 5.371470024329028e-07, "source": "2534"}], "hostgstackDetectID": [{"value": 2.523220917274808e+18, "source": "2534"}], "hostgstackImageID": [{"value": 4489444.0, "source": "2534"}], "hostgxPos": [{"value": 2827.68994140625, "source": "2534"}], "hostgxPosErr": [{"value": 0.009525679983198644, "source": "2534"}], "hostgyPos": [{"value": 5758.52978515625, "source": "2534"}], "hostgyPosErr": [{"value": 0.009216089732944964, "source": "2534"}], "hostgzp": [{"value": 24.98900032043457, "source": "2534"}], "hosthtmID": [{"value": 16471965287794, "source": "2534"}], "hosti-z": [{"value": 0.13279914855956676, "source": "2534"}], "hosti-zErr": [{"value": 0.001207685828996626, "source": "2534"}], "hostiApFillFac": [{"value": 0.8839020133018494, "source": "2534"}], "hostiApFlux": [{"value": 0.0006797949899919331, "source": "2534"}], "hostiApFluxErr": [{"value": 4.64121995946698e-07, "source": "2534"}], "hostiApMag": [{"value": 16.819099426269528, "source": "2534"}], "hostiApMagErr": [{"value": 0.0006830000202171503, "source": "2534"}], "hostiApMag_iKronMag": [{"value": 1.1605997085571254, "source": "2534"}], "hostiApRadius": [{"value": 2.75, "source": "2534"}], "hostiEpoch": [{"value": 56080.75287330001, "source": "2534"}], "hostiExtNSigma": [{"value": 28.345399856567386, "source": "2534"}], "hostiKronFlux": [{"value": 0.0019796499982476234, "source": "2534"}], "hostiKronFluxErr": [{"value": 3.355489980094717e-06, "source": "2534"}], "hostiKronMag": [{"value": 15.658499717712402, "source": "2534"}], "hostiKronMagErr": [{"value": 0.0016949999844655395, "source": "2534"}], "hostiKronRad": [{"value": 11.953399658203125, "source": "2534"}], "hostiPSFFlux": [{"value": 0.0002581280132289976, "source": "2534"}], "hostiPSFFluxErr": [{"value": 5.858390181856521e-07, "source": "2534"}], "hostiPSFMag": [{"value": 17.870399475097656, "source": "2534"}], "hostiPSFMagErr": [{"value": 0.00227000005543232, "source": "2534"}], "hostiPlateScale": [{"value": 0.25, "source": "2534"}], "hostidec": [{"value": 29.98093615, "source": "2534"}], "hostidecErr": [{"value": 0.000955883995629847, "source": "2534"}], "hostiexpTime": [{"value": 1260.0, "source": "2534"}], "hostiinfoFlag": [{"value": 262160391.0, "source": "2534"}], "hostiinfoFlag2": [{"value": 524416.0, "source": "2534"}], "hostiinfoFlag3": [{"value": 196608.0, "source": "2534"}], "hostiippDetectID": [{"value": 3704.0, "source": "2534"}], "hostimomentR1": [{"value": 4.781370162963867, "source": "2534"}], "hostimomentRH": [{"value": 1.1715600490570068, "source": "2534"}], "hostimomentXX": [{"value": 0.31822699308395386, "source": "2534"}], "hostimomentXY": [{"value": -0.0008952519856393338, "source": "2534"}], "hostimomentYY": [{"value": 0.3131909966468811, "source": "2534"}], "hostinFrames": [{"value": 22.0, "source": "2534"}], "hostippObjID": [{"value": 175986285007154, "source": "2534"}], "hostipsfChiSq": [{"value": 229.4579925537109, "source": "2534"}], "hostipsfCore": [{"value": 0.8231850266456604, "source": "2534"}], "hostipsfLikelihood": [{"value": 0.0, "source": "2534"}], "hostipsfMajorFWHM": [{"value": 1.071660041809082, "source": "2534"}], "hostipsfMinorFWHM": [{"value": 1.0127500295639038, "source": "2534"}], "hostipsfQf": [{"value": 0.9986029863357544, "source": "2534"}], "hostipsfQfPerfect": [{"value": 0.9986029863357544, "source": "2534"}], "hostipsfTheta": [{"value": 58.04710006713867, "source": "2534"}], "hostira": [{"value": 127.38743961, "source": "2534"}], "hostiraErr": [{"value": 0.0010312700178474188, "source": "2534"}], "hostisky": [{"value": 2.5757600496945088e-08, "source": "2534"}], "hostiskyErr": [{"value": 7.564000270576798e-07, "source": "2534"}], "hostistackDetectID": [{"value": 2.523221216311906e+18, "source": "2534"}], "hostistackImageID": [{"value": 4490558.0, "source": "2534"}], "hostixPos": [{"value": 2827.679931640625, "source": "2534"}], "hostixPosErr": [{"value": 0.004125060047954321, "source": "2534"}], "hostiyPos": [{"value": 5758.31982421875, "source": "2534"}], "hostiyPosErr": [{"value": 0.003823529928922653, "source": "2534"}], "hostizp": [{"value": 24.99449920654297, "source": "2534"}], "hostl": [{"value": 193.32112129123686, "source": "2534"}], "hostlambda": [{"value": 122.35491256903204, "source": "2534"}], "hostnDetections": [{"value": 76, "source": "2534"}], "hostnStackDetections": [{"value": 5, "source": "2534"}], "hostng": [{"value": 12, "source": "2534"}], "hostni": [{"value": 22, "source": "2534"}], "hostnr": [{"value": 12, "source": "2534"}], "hostny": [{"value": 15, "source": "2534"}], "hostnz": [{"value": 15, "source": "2534"}], "hostobjID": [{"value": 143971273874317683, "source": "2534"}], "hostobjInfoFlag": [{"value": 512024576, "source": "2534"}], "hostobjName": [{"value": "PSO J082932.985+295851.343", "source": "2534"}], "hostposMeanChisq": [{"value": 2.618499994277954, "source": "2534"}], "hostprimaryDetection": [{"value": 1, "source": "2534"}], "hostprocessingVersion": [{"value": 3, "source": "2534"}], "hostprojectionID": [{"value": 1958.0, "source": "2534"}], "hostqualityFlag": [{"value": 61, "source": "2534"}], "hostr-i": [{"value": 0.3269004821777379, "source": "2534"}], "hostr-iErr": [{"value": 0.0012736224346754008, "source": "2534"}], "hostrApFillFac": [{"value": 0.8996679782867432, "source": "2534"}], "hostrApFlux": [{"value": 0.0005030499887652695, "source": "2534"}], "hostrApFluxErr": [{"value": 5.409049776972097e-07, "source": "2534"}], "hostrApMag": [{"value": 17.145999908447266, "source": "2534"}], "hostrApMagErr": [{"value": 0.001075000036507845, "source": "2534"}], "hostrApMag_rKronMag": [{"value": 1.1040992736816406, "source": "2534"}], "hostrApRadius": [{"value": 3.0, "source": "2534"}], "hostrEpoch": [{"value": 55883.1108536, "source": "2534"}], "hostrExtNSigma": [{"value": 27.54319953918457, "source": "2534"}], "hostrKronFlux": [{"value": 0.0013907799730077384, "source": "2534"}], "hostrKronFluxErr": [{"value": 3.2628699955239426e-06, "source": "2534"}], "hostrKronMag": [{"value": 16.041900634765625, "source": "2534"}], "hostrKronMagErr": [{"value": 0.0023459999356418852, "source": "2534"}], "hostrKronRad": [{"value": 11.762100219726562, "source": "2534"}], "hostrPSFFlux": [{"value": 0.00014284100325312463, "source": "2534"}], "hostrPSFFluxErr": [{"value": 6.238669811864386e-07, "source": "2534"}], "hostrPSFMag": [{"value": 18.51289939880371, "source": "2534"}], "hostrPSFMagErr": [{"value": 0.0043680001981556416, "source": "2534"}], "hostrPlateScale": [{"value": 0.25, "source": "2534"}], "hostraMean": [{"value": 127.38745106, "source": "2534"}], "hostraMeanErr": [{"value": 0.003490000031888485, "source": "2534"}], "hostraStack": [{"value": 127.38743961, "source": "2534"}], "hostraStackErr": [{"value": 0.0010000000474974509, "source": "2534"}], "hostrandomID": [{"value": 0.345250852727565, "source": "2534"}], "hostrdec": [{"value": 29.98075192, "source": "2534"}], "hostrdecErr": [{"value": 0.002025360008701682, "source": "2534"}], "hostrexpTime": [{"value": 662.0, "source": "2534"}], "hostrinfoFlag": [{"value": 262160391.0, "source": "2534"}], "hostrinfoFlag2": [{"value": 524416.0, "source": "2534"}], "hostrinfoFlag3": [{"value": 196608.0, "source": "2534"}], "hostrippDetectID": [{"value": 3704.0, "source": "2534"}], "hostrmomentR1": [{"value": 4.704820156097412, "source": "2534"}], "hostrmomentRH": [{"value": 1.1946500539779663, "source": "2534"}], "hostrmomentXX": [{"value": 0.3749719858169556, "source": "2534"}], "hostrmomentXY": [{"value": -0.0031559900380671024, "source": "2534"}], "hostrmomentYY": [{"value": 0.3914650082588196, "source": "2534"}], "hostrnFrames": [{"value": 10.0, "source": "2534"}], "hostrpsfChiSq": [{"value": 117.072998046875, "source": "2534"}], "hostrpsfCore": [{"value": 0.5655350089073181, "source": "2534"}], "hostrpsfLikelihood": [{"value": 0.0, "source": "2534"}], "hostrpsfMajorFWHM": [{"value": 1.1017299890518188, "source": "2534"}], "hostrpsfMinorFWHM": [{"value": 1.0899499654769895, "source": "2534"}], "hostrpsfQf": [{"value": 0.9993000030517578, "source": "2534"}], "hostrpsfQfPerfect": [{"value": 0.9993000030517578, "source": "2534"}], "hostrpsfTheta": [{"value": -5.783170223236084, "source": "2534"}], "hostrra": [{"value": 127.38740277, "source": "2534"}], "hostrraErr": [{"value": 0.0020766400266438727, "source": "2534"}], "hostrsky": [{"value": 2.142730082255184e-08, "source": "2534"}], "hostrskyErr": [{"value": 6.731110033797449e-07, "source": "2534"}], "hostrstackDetectID": [{"value": 2.5232261998161464e+18, "source": "2534"}], "hostrstackImageID": [{"value": 4509123.0, "source": "2534"}], "hostrxPos": [{"value": 2828.14990234375, "source": "2534"}], "hostrxPosErr": [{"value": 0.008306549862027168, "source": "2534"}], "hostryPos": [{"value": 5755.669921875, "source": "2534"}], "hostryPosErr": [{"value": 0.008101419545710087, "source": "2534"}], "hostrzp": [{"value": 25.010499954223643, "source": "2534"}], "hostskyCellID": [{"value": 45, "source": "2534"}], "hostsurveyID": [{"value": 0, "source": "2534"}], "hosttessID": [{"value": 1, "source": "2534"}], "hostuniquePspsOBid": [{"value": 1038846000053554, "source": "2534"}], "hostuniquePspsSTid": [{"value": 1108868000002834, "source": "2534"}], "hostyApFillFac": [{"value": 0.8684750199317932, "source": "2534"}], "hostyApFlux": [{"value": 0.0007677919929847121, "source": "2534"}], "hostyApFluxErr": [{"value": 7.272630000443313e-07, "source": "2534"}], "hostyApMag": [{"value": 16.686899185180664, "source": "2534"}], "hostyApMagErr": [{"value": 0.0009469999931752682, "source": "2534"}], "hostyApMag_yKronMag": [{"value": 1.3769989013671893, "source": "2534"}], "hostyApRadius": [{"value": 2.25, "source": "2534"}], "hostyEpoch": [{"value": 56116.248547099996, "source": "2534"}], "hostyExtNSigma": [{"value": 33.59650039672852, "source": "2534"}], "hostyKronFlux": [{"value": 0.002729309955611825, "source": "2534"}], "hostyKronFluxErr": [{"value": 1.5958299627527595e-05, "source": "2534"}], "hostyKronMag": [{"value": 15.309900283813475, "source": "2534"}], "hostyKronMagErr": [{"value": 0.005847000051289797, "source": "2534"}], "hostyKronRad": [{"value": 10.62689971923828, "source": "2534"}], "hostyPSFFlux": [{"value": 0.00027463200967758894, "source": "2534"}], "hostyPSFFluxErr": [{"value": 2.23744996219466e-06, "source": "2534"}], "hostyPSFMag": [{"value": 17.8031005859375, "source": "2534"}], "hostyPSFMagErr": [{"value": 0.008147000335156921, "source": "2534"}], "hostyPlateScale": [{"value": 0.25, "source": "2534"}], "hostydec": [{"value": 29.98092242, "source": "2534"}], "hostydecErr": [{"value": 0.0028946299571543928, "source": "2534"}], "hostyexpTime": [{"value": 590.0, "source": "2534"}], "hostyinfoFlag": [{"value": 262160391.0, "source": "2534"}], "hostyinfoFlag2": [{"value": 524416.0, "source": "2534"}], "hostyinfoFlag3": [{"value": 196608.0, "source": "2534"}], "hostyippDetectID": [{"value": 3704.0, "source": "2534"}], "hostymomentR1": [{"value": 4.250770092010498, "source": "2534"}], "hostymomentRH": [{"value": 1.0476200580596924, "source": "2534"}], "hostymomentXX": [{"value": 0.20473000407218933, "source": "2534"}], "hostymomentXY": [{"value": -0.0002977210097014904, "source": "2534"}], "hostymomentYY": [{"value": 0.19902099668979645, "source": "2534"}], "hostynFrames": [{"value": 13.0, "source": "2534"}], "hostypsfChiSq": [{"value": 21.0137996673584, "source": "2534"}], "hostypsfCore": [{"value": 0.4560230076313019, "source": "2534"}], "hostypsfLikelihood": [{"value": 0.0, "source": "2534"}], "hostypsfMajorFWHM": [{"value": 0.9050930142402648, "source": "2534"}], "hostypsfMinorFWHM": [{"value": 0.8622210025787354, "source": "2534"}], "hostypsfQf": [{"value": 0.9977909922599792, "source": "2534"}], "hostypsfQfPerfect": [{"value": 0.9977909922599792, "source": "2534"}], "hostypsfTheta": [{"value": -16.712699890136722, "source": "2534"}], "hostyra": [{"value": 127.3874361, "source": "2534"}], "hostyraErr": [{"value": 0.003031230065971613, "source": "2534"}], "hostysky": [{"value": 8.464959933007776e-08, "source": "2534"}], "hostyskyErr": [{"value": 4.159379841439659e-06, "source": "2534"}], "hostystackDetectID": [{"value": 2.523223115224321e+18, "source": "2534"}], "hostystackImageID": [{"value": 4497632.0, "source": "2534"}], "hostyxPos": [{"value": 2827.72998046875, "source": "2534"}], "hostyxPosErr": [{"value": 0.01212489977478981, "source": "2534"}], "hostyyPos": [{"value": 5758.10986328125, "source": "2534"}], "hostyyPosErr": [{"value": 0.011578500270843506, "source": "2534"}], "hostyzp": [{"value": 25.043100357055664, "source": "2534"}], "hostz-y": [{"value": -0.000598907470703125, "source": "2534"}], "hostz-yErr": [{"value": 0.0013743453063246509, "source": "2534"}], "hostzApFillFac": [{"value": 0.8839020133018494, "source": "2534"}], "hostzApFlux": [{"value": 0.0007682249997742474, "source": "2534"}], "hostzApFluxErr": [{"value": 7.648629889445147e-07, "source": "2534"}], "hostzApMag": [{"value": 16.68630027770996, "source": "2534"}], "hostzApMagErr": [{"value": 0.0009960000170394778, "source": "2534"}], "hostzApMag_zKronMag": [{"value": 1.1289005279541016, "source": "2534"}], "hostzApRadius": [{"value": 2.7499899864196777, "source": "2534"}], "hostzEpoch": [{"value": 55829.3215083, "source": "2534"}], "hostzExtNSigma": [{"value": 41.40359878540039, "source": "2534"}], "hostzKronFlux": [{"value": 0.002172870095819236, "source": "2534"}], "hostzKronFluxErr": [{"value": 6.569040124304592e-06, "source": "2534"}], "hostzKronMag": [{"value": 15.55739974975586, "source": "2534"}], "hostzKronMagErr": [{"value": 0.003022999968379736, "source": "2534"}], "hostzKronRad": [{"value": 11.245800018310547, "source": "2534"}], "hostzPSFFlux": [{"value": 0.00028833700343966484, "source": "2534"}], "hostzPSFFluxErr": [{"value": 1.1118299880763516e-06, "source": "2534"}], "hostzPSFMag": [{"value": 17.750200271606445, "source": "2534"}], "hostzPSFMagErr": [{"value": 0.003856000024825335, "source": "2534"}], "hostzPlateScale": [{"value": 0.25, "source": "2534"}], "hostzdec": [{"value": 29.98092862, "source": "2534"}], "hostzdecErr": [{"value": 0.001785550033673644, "source": "2534"}], "hostzexpTime": [{"value": 510.0, "source": "2534"}], "hostzinfoFlag": [{"value": 262160391.0, "source": "2534"}], "hostzinfoFlag2": [{"value": 524416.0, "source": "2534"}], "hostzinfoFlag3": [{"value": 196608.0, "source": "2534"}], "hostzippDetectID": [{"value": 3704.0, "source": "2534"}], "hostzmomentR1": [{"value": 4.498330116271973, "source": "2534"}], "hostzmomentRH": [{"value": 1.1563999652862549, "source": "2534"}], "hostzmomentXX": [{"value": 0.3043369948863983, "source": "2534"}], "hostzmomentXY": [{"value": -0.0010649299947544932, "source": "2534"}], "hostzmomentYY": [{"value": 0.2988229990005493, "source": "2534"}], "hostznFrames": [{"value": 15.0, "source": "2534"}], "hostzoneID": [{"value": 14397, "source": "2534"}], "hostzpsfChiSq": [{"value": 76.90589904785156, "source": "2534"}], "hostzpsfCore": [{"value": 0.2768070101737976, "source": "2534"}], "hostzpsfLikelihood": [{"value": 0.0, "source": "2534"}], "hostzpsfMajorFWHM": [{"value": 1.1417399644851685, "source": "2534"}], "hostzpsfMinorFWHM": [{"value": 1.130020022392273, "source": "2534"}], "hostzpsfQf": [{"value": 0.9984369874000548, "source": "2534"}], "hostzpsfQfPerfect": [{"value": 0.9984369874000548, "source": "2534"}], "hostzpsfTheta": [{"value": 89.08989715576172, "source": "2534"}], "hostzra": [{"value": 127.38744848, "source": "2534"}], "hostzraErr": [{"value": 0.0018216200405731802, "source": "2534"}], "hostzsky": [{"value": 4.2281399714738654e-08, "source": "2534"}], "hostzskyErr": [{"value": 1.5535399597865762e-06, "source": "2534"}], "hostzstackDetectID": [{"value": 2.5232217749260897e+18, "source": "2534"}], "hostzstackImageID": [{"value": 4492639.0, "source": "2534"}], "hostzxPos": [{"value": 2827.580078125, "source": "2534"}], "hostzxPosErr": [{"value": 0.007286500185728073, "source": "2534"}], "hostzyPos": [{"value": 5758.2099609375, "source": "2534"}], "hostzyPosErr": [{"value": 0.00714220991358161, "source": "2534"}], "hostzzp": [{"value": 25.01810073852539, "source": "2534"}]}}